{
  "facturas_emitidas": [
    {
      "fecha": "2025-07-04",
      "fecha_imputacion": "2025-07-17",
      "no_fact": "B0100000132",
      "tipo_factura": "Factura Privada",
      "moneda": "RD$",
      "rnc": "131296892",
      "empresa": "CENTRO DE SALUD DENTAL DRA. GISELA SAPEG",
      "itbis": 0.0,
      "factura_total": 54735.0,
      "tasa_conversion": 1.0,
      "monto_convertido_rd": 54735.0
    },
    {
      "fecha": "2025-06-02",
      "fecha_imputacion": "2025-07-18",
      "no_fact": "B0100000130",
      "tipo_factura": "Factura Privada",
      "moneda": "RD$",
      "rnc": "131296892",
      "empresa": "CENTRO DE SALUD DENTAL DRA. GISELA SAPEG",
      "itbis": 0.0,
      "factura_total": 46477.0,
      "tasa_conversion": 1.0,
      "monto_convertido_rd": 46477.0
    },
    {
      "fecha": "2025-06-23",
      "fecha_imputacion": "2025-07-18",
      "no_fact": "B0100000131",
      "tipo_factura": "Factura Privada",
      "moneda": "RD$",
      "rnc": "131358472",
      "empresa": "APME",
      "itbis": 1632.06,
      "factura_total": 10699.06,
      "tasa_conversion": 1.0,
      "monto_convertido_rd": 10699.06
    },
    {
      "fecha": "2025-06-09",
      "fecha_imputacion": "2025-07-18",
      "no_fact": "B1500000057",
      "tipo_factura": "Factura Gubernamental",
      "moneda": "RD$",
      "rnc": "401007339",
      "empresa": "MINISTERIO DE EDUCACION (MINERD)",
      "itbis": 32877.0,
      "factura_total": 215527.0,
      "tasa_conversion": 1.0,
      "monto_convertido_rd": 215527.0
    },
    {
      "fecha": "2025-06-17",
      "fecha_imputacion": "2025-07-18",
      "no_fact": "B1500000058",
      "tipo_factura": "Factura Gubernamental",
      "moneda": "RD$",
      "rnc": "401039249",
      "empresa": "DIRECCION GENERAL DE ADUANAS Y PUERTOS",
      "itbis": 37656.0,
      "factura_total": 246856.0,
      "tasa_conversion": 1.0,
      "monto_convertido_rd": 246856.0
    },
    {
      "fecha": "2025-07-04",
      "fecha_imputacion": "2025-08-04",
      "no_fact": "B0100000132",
      "tipo_factura": "Factura Privada",
      "moneda": "RD$",
      "rnc": "131296892",
      "empresa": "CENTRO DE SALUD DRA. GISELA SAPEG",
      "itbis": 0.0,
      "factura_total": 54735.0,
      "tasa_conversion": 1.0,
      "monto_convertido_rd": 54735.0
    },
    {
      "fecha": "2025-07-16",
      "fecha_imputacion": "2025-08-04",
      "no_fact": "B0100000133",
      "tipo_factura": "Factura Privada",
      "moneda": "RD$",
      "rnc": "133088266",
      "empresa": "KOREX SRL",
      "itbis": 12510.0,
      "factura_total": 82010.0,
      "tasa_conversion": 1.0,
      "monto_convertido_rd": 82010.0
    },
    {
      "fecha": "2025-07-31",
      "fecha_imputacion": "2025-08-04",
      "no_fact": "B1500000059",
      "tipo_factura": "Factura Gubernamental",
      "moneda": "RD$",
      "rnc": "401039249",
      "empresa": "DIRECCION GENERAL DE ADUANAS Y PUERTOS",
      "itbis": 37602.0,
      "factura_total": 246502.0,
      "tasa_conversion": 1.0,
      "monto_convertido_rd": 246502.0
    },
    {
      "fecha": "2025-08-04",
      "fecha_imputacion": "2025-09-01",
      "no_fact": "B0100000134",
      "tipo_factura": "Factura Privada",
      "moneda": "RD$",
      "rnc": "131296892",
      "empresa": "CENTRO DE SALUD DRA. GISELA SAPEG",
      "itbis": 0.0,
      "factura_total": 59488.0,
      "tasa_conversion": 1.0,
      "monto_convertido_rd": 59488.0
    },
    {
      "fecha": "2025-08-26",
      "fecha_imputacion": "2025-09-01",
      "no_fact": "B0100000135",
      "tipo_factura": "Factura Privada",
      "moneda": "RD$",
      "rnc": "133088266",
      "empresa": "KOREX SRL",
      "itbis": 35084.75,
      "factura_total": 230000.0,
      "tasa_conversion": 1.0,
      "monto_convertido_rd": 230000.0
    },
    {
      "fecha": "2025-08-27",
      "fecha_imputacion": "2025-09-01",
      "no_fact": "B1500000060",
      "tipo_factura": "Factura Gubernamental",
      "moneda": "RD$",
      "rnc": "401039249",
      "empresa": "DIRECCION GENERAL DE ADUANAS Y PUERTOS",
      "itbis": 37350.0,
      "factura_total": 244850.0,
      "tasa_conversion": 1.0,
      "monto_convertido_rd": 244850.0
    },
    {
      "fecha": "2025-08-27",
      "fecha_imputacion": "2025-09-01",
      "no_fact": "B1500000061 ",
      "tipo_factura": "Factura Privada",
      "moneda": "RD$",
      "rnc": "401039249",
      "empresa": "DIRECCION GENERAL DE ADUANAS Y PUERTOS",
      "itbis": 37692.0,
      "factura_total": 247092.0,
      "tasa_conversion": 1.0,
      "monto_convertido_rd": 247092.0
    }
  ],
  "facturas_gastos": [
    {
      "fecha": "2025-07-13",
      "fecha_imputacion": "2025-07-17",
      "no_fact": "E310002367405",
      "rnc": "101019921",
      "lugar_compra": "CENTRO CUESTA NACIONAL",
      "moneda": "RD$",
      "itbis": 111.05,
      "factura_total": 1640.0,
      "tasa_conversion": 1.0,
      "monto_convertido_rd": 1640.0
    },
    {
      "fecha": "2025-07-09",
      "fecha_imputacion": "2025-07-17",
      "no_fact": "412276",
      "rnc": "130343561",
      "lugar_compra": "D COLOR AUTO PAINT",
      "moneda": "RD$",
      "itbis": 2010.52,
      "factura_total": 13180.06,
      "tasa_conversion": 1.0,
      "monto_convertido_rd": 13180.06
    },
    {
      "fecha": "2025-07-17",
      "fecha_imputacion": "2025-07-17",
      "no_fact": "1760235",
      "rnc": "131010148",
      "lugar_compra": "FOODHALL HOLDING SRL",
      "moneda": "RD$",
      "itbis": 1228.5,
      "factura_total": 8736.0,
      "tasa_conversion": 1.0,
      "monto_convertido_rd": 8736.0
    },
    {
      "fecha": "2025-07-04",
      "fecha_imputacion": "2025-07-17",
      "no_fact": "E310007901691",
      "rnc": "101602465",
      "lugar_compra": "BRAVO S.A",
      "moneda": "RD$",
      "itbis": 304.93,
      "factura_total": 3481.0,
      "tasa_conversion": 1.0,
      "monto_convertido_rd": 3481.0
    },
    {
      "fecha": "2025-07-05",
      "fecha_imputacion": "2025-07-17",
      "no_fact": "E310000342763",
      "rnc": "101801875",
      "lugar_compra": "PRICESMART",
      "moneda": "RD$",
      "itbis": 399.66,
      "factura_total": 2695.0,
      "tasa_conversion": 1.0,
      "monto_convertido_rd": 2695.0
    },
    {
      "fecha": "2025-07-10",
      "fecha_imputacion": "2025-07-17",
      "no_fact": "E310000000240",
      "rnc": "132225155",
      "lugar_compra": "CERAMIECO SRL",
      "moneda": "RD$",
      "itbis": 2631.35,
      "factura_total": 17250.0,
      "tasa_conversion": 1.0,
      "monto_convertido_rd": 17250.0
    },
    {
      "fecha": "2025-07-06",
      "fecha_imputacion": "2025-07-17",
      "no_fact": "E310000000759",
      "rnc": "00112812326",
      "lugar_compra": "ESPAÑOLERIAS",
      "moneda": "RD$",
      "itbis": 152.54,
      "factura_total": 1000.0,
      "tasa_conversion": 1.0,
      "monto_convertido_rd": 1000.0
    },
    {
      "fecha": "2025-07-09",
      "fecha_imputacion": "2025-07-17",
      "no_fact": "140065",
      "rnc": "130689164",
      "lugar_compra": "SIGMA PETROLEUM CORP",
      "moneda": "RD$",
      "itbis": 0.0,
      "factura_total": 3000.0,
      "tasa_conversion": 1.0,
      "monto_convertido_rd": 3000.0
    },
    {
      "fecha": "2025-07-05",
      "fecha_imputacion": "2025-07-17",
      "no_fact": "B0100674300",
      "rnc": "401051712",
      "lugar_compra": "CLUB DEPORTIVO NAVO",
      "moneda": "RD$",
      "itbis": 163.5,
      "factura_total": 1798.5,
      "tasa_conversion": 1.0,
      "monto_convertido_rd": 1798.5
    },
    {
      "fecha": "2025-07-01",
      "fecha_imputacion": "2025-07-17",
      "no_fact": "B011982117800000000",
      "rnc": "101019921",
      "lugar_compra": "CENTRO CUESTA NACIONAL",
      "moneda": "RD$",
      "itbis": 129.76,
      "factura_total": 1368.18,
      "tasa_conversion": 1.0,
      "monto_convertido_rd": 1368.18
    },
    {
      "fecha": "2025-06-30",
      "fecha_imputacion": "2025-07-17",
      "no_fact": "E310007899577",
      "rnc": "101602465",
      "lugar_compra": "BRAVO S.A",
      "moneda": "RD$",
      "itbis": 179.88,
      "factura_total": 1761.0,
      "tasa_conversion": 1.0,
      "monto_convertido_rd": 1761.0
    },
    {
      "fecha": "2025-06-22",
      "fecha_imputacion": "2025-07-17",
      "no_fact": "E310002245998",
      "rnc": "101801875",
      "lugar_compra": "PRICESMART",
      "moneda": "RD$",
      "itbis": 173.13,
      "factura_total": 1570.0,
      "tasa_conversion": 1.0,
      "monto_convertido_rd": 1570.0
    },
    {
      "fecha": "2025-06-30",
      "fecha_imputacion": "2025-07-17",
      "no_fact": "E310000081572",
      "rnc": "130064423",
      "lugar_compra": "FARMACIA MEDICAR GBC SRL",
      "moneda": "RD$",
      "itbis": 0.0,
      "factura_total": 6846.39,
      "tasa_conversion": 1.0,
      "monto_convertido_rd": 6846.39
    },
    {
      "fecha": "2025-06-28",
      "fecha_imputacion": "2025-07-17",
      "no_fact": "E310000226403",
      "rnc": "124003091",
      "lugar_compra": "KENTUCKY FOODS GROUP LIMITED",
      "moneda": "RD$",
      "itbis": 228.81,
      "factura_total": 1499.0,
      "tasa_conversion": 1.0,
      "monto_convertido_rd": 1499.0
    },
    {
      "fecha": "2025-06-29",
      "fecha_imputacion": "2025-07-17",
      "no_fact": "E310000190167",
      "rnc": "130389586",
      "lugar_compra": "JADE TERIYAKI",
      "moneda": "RD$",
      "itbis": 160.17,
      "factura_total": 1049.99,
      "tasa_conversion": 1.0,
      "monto_convertido_rd": 1049.99
    },
    {
      "fecha": "2025-07-08",
      "fecha_imputacion": "2025-07-17",
      "no_fact": "E310000349091",
      "rnc": "101802456",
      "lugar_compra": "COMPAÑIA DOMINICANA DE HIPERMERCADOS CDH",
      "moneda": "RD$",
      "itbis": 206.9,
      "factura_total": 2086.56,
      "tasa_conversion": 1.0,
      "monto_convertido_rd": 2086.56
    },
    {
      "fecha": "2025-07-11",
      "fecha_imputacion": "2025-07-17",
      "no_fact": "B0100003410",
      "rnc": "131526578",
      "lugar_compra": "INVERSIONES MORLESTHER SRL",
      "moneda": "RD$",
      "itbis": 370.98,
      "factura_total": 2432.0,
      "tasa_conversion": 1.0,
      "monto_convertido_rd": 2432.0
    },
    {
      "fecha": "2025-07-10",
      "fecha_imputacion": "2025-07-17",
      "no_fact": "B0100043175",
      "rnc": "131984924",
      "lugar_compra": "RESTAURANCITO",
      "moneda": "RD$",
      "itbis": 458.1,
      "factura_total": 3257.6,
      "tasa_conversion": 1.0,
      "monto_convertido_rd": 3257.6
    },
    {
      "fecha": "2025-07-10",
      "fecha_imputacion": "2025-07-17",
      "no_fact": "B0100043174",
      "rnc": "131984924",
      "lugar_compra": "RESTAURANCITO",
      "moneda": "RD$",
      "itbis": 1144.07,
      "factura_total": 7500.0,
      "tasa_conversion": 1.0,
      "monto_convertido_rd": 7500.0
    },
    {
      "fecha": "2025-07-11",
      "fecha_imputacion": "2025-07-17",
      "no_fact": "B0100004638",
      "rnc": "130983607",
      "lugar_compra": "DR RAFAEL SANTOS PELEGRIN",
      "moneda": "RD$",
      "itbis": 0.0,
      "factura_total": 23235.0,
      "tasa_conversion": 1.0,
      "monto_convertido_rd": 23235.0
    },
    {
      "fecha": "2025-07-06",
      "fecha_imputacion": "2025-07-17",
      "no_fact": "E310000331493",
      "rnc": "101802456",
      "lugar_compra": "COMPAÑIA DOMINICANA DE HIPERMERCADOS CDH",
      "moneda": "RD$",
      "itbis": 167.6,
      "factura_total": 2231.15,
      "tasa_conversion": 1.0,
      "monto_convertido_rd": 2231.15
    },
    {
      "fecha": "2025-07-07",
      "fecha_imputacion": "2025-07-17",
      "no_fact": "E310007902525",
      "rnc": "101602465",
      "lugar_compra": "BRAVO S.A",
      "moneda": "RD$",
      "itbis": 149.04,
      "factura_total": 1842.0,
      "tasa_conversion": 1.0,
      "monto_convertido_rd": 1842.0
    },
    {
      "fecha": "2025-07-06",
      "fecha_imputacion": "2025-07-17",
      "no_fact": "B0100514109",
      "rnc": "101767766",
      "lugar_compra": "ESTACION AXXON",
      "moneda": "RD$",
      "itbis": 0.0,
      "factura_total": 3341.0,
      "tasa_conversion": 1.0,
      "monto_convertido_rd": 3341.0
    },
    {
      "fecha": "2025-07-14",
      "fecha_imputacion": "2025-07-17",
      "no_fact": "1110714",
      "rnc": "101068744",
      "lugar_compra": "TOTAL ENERGIES",
      "moneda": "RD$",
      "itbis": 0.0,
      "factura_total": 4203.8,
      "tasa_conversion": 1.0,
      "monto_convertido_rd": 4203.8
    },
    {
      "fecha": "2025-07-05",
      "fecha_imputacion": "2025-07-17",
      "no_fact": "22983257",
      "rnc": "131038913",
      "lugar_compra": "JAS SOSA SERVICIOS SRL",
      "moneda": "RD$",
      "itbis": 788.72,
      "factura_total": 5170.5,
      "tasa_conversion": 1.0,
      "monto_convertido_rd": 5170.5
    },
    {
      "fecha": "2025-07-02",
      "fecha_imputacion": "2025-07-17",
      "no_fact": "B0119821551",
      "rnc": "101019921",
      "lugar_compra": "CENTRO CUESTA NACIONAL",
      "moneda": "RD$",
      "itbis": 62.51,
      "factura_total": 1729.86,
      "tasa_conversion": 1.0,
      "monto_convertido_rd": 1729.86
    },
    {
      "fecha": "2025-07-10",
      "fecha_imputacion": "2025-07-17",
      "no_fact": "B0100004768",
      "rnc": "132025334",
      "lugar_compra": "LANTIGUA ELECTRO INDUSTRIAL SRL",
      "moneda": "RD$",
      "itbis": 15010.27,
      "factura_total": 98400.67,
      "tasa_conversion": 1.0,
      "monto_convertido_rd": 98400.67
    },
    {
      "fecha": "2025-07-15",
      "fecha_imputacion": "2025-07-17",
      "no_fact": "0000389977",
      "rnc": "101617233",
      "lugar_compra": "PREMIUM & CO SRL",
      "moneda": "RD$",
      "itbis": 2388.61,
      "factura_total": 15658.69,
      "tasa_conversion": 1.0,
      "monto_convertido_rd": 15658.69
    },
    {
      "fecha": "2025-07-15",
      "fecha_imputacion": "2025-07-17",
      "no_fact": "B0100004782",
      "rnc": "132025334",
      "lugar_compra": "LANTIGUA ELECTRO INDUSTRIAL SRL",
      "moneda": "RD$",
      "itbis": 6504.12,
      "factura_total": 42638.12,
      "tasa_conversion": 1.0,
      "monto_convertido_rd": 42638.12
    },
    {
      "fecha": "2025-07-16",
      "fecha_imputacion": "2025-07-17",
      "no_fact": "B0119825743",
      "rnc": "101019921",
      "lugar_compra": "CENTRO CUESTA NACIONAL",
      "moneda": "RD$",
      "itbis": 252.66,
      "factura_total": 3488.24,
      "tasa_conversion": 1.0,
      "monto_convertido_rd": 3488.24
    },
    {
      "fecha": "2025-07-18",
      "fecha_imputacion": "2025-07-18",
      "no_fact": "B0100004793",
      "rnc": "132025334",
      "lugar_compra": "LANTIGUA ELECTRO INDUSTRIAL SRL",
      "moneda": "RD$",
      "itbis": 7506.0,
      "factura_total": 49206.0,
      "tasa_conversion": 1.0,
      "monto_convertido_rd": 49206.0
    },
    {
      "fecha": "2025-07-17",
      "fecha_imputacion": "2025-07-22",
      "no_fact": "327264",
      "rnc": "130941483",
      "lugar_compra": "INVERSIONES EGUREN SRL",
      "moneda": "RD$",
      "itbis": 340.2,
      "factura_total": 2419.2,
      "tasa_conversion": 1.0,
      "monto_convertido_rd": 2419.2
    },
    {
      "fecha": "2025-07-19",
      "fecha_imputacion": "2025-07-22",
      "no_fact": "166904",
      "rnc": "133013428",
      "lugar_compra": "CASSAVA CARIBBEAN FOOD COURT SRL",
      "moneda": "RD$",
      "itbis": 1601.1,
      "factura_total": 11385.6,
      "tasa_conversion": 1.0,
      "monto_convertido_rd": 11385.6
    },
    {
      "fecha": "2025-07-18",
      "fecha_imputacion": "2025-07-22",
      "no_fact": "E310000001068",
      "rnc": "00112812326",
      "lugar_compra": "ESPAÑOLERIAS",
      "moneda": "RD$",
      "itbis": 499.58,
      "factura_total": 3275.01,
      "tasa_conversion": 1.0,
      "monto_convertido_rd": 3275.01
    },
    {
      "fecha": "2025-07-17",
      "fecha_imputacion": "2025-07-22",
      "no_fact": "B0119165271",
      "rnc": "101019921",
      "lugar_compra": "CENTRO CUESTA NACIONAL",
      "moneda": "RD$",
      "itbis": 296.92,
      "factura_total": 1946.5,
      "tasa_conversion": 1.0,
      "monto_convertido_rd": 1946.5
    },
    {
      "fecha": "2025-07-19",
      "fecha_imputacion": "2025-07-22",
      "no_fact": "B0100084445",
      "rnc": "130500142",
      "lugar_compra": "LAUREL FOOD & WINE",
      "moneda": "RD$",
      "itbis": 2383.2,
      "factura_total": 16947.2,
      "tasa_conversion": 1.0,
      "monto_convertido_rd": 16947.2
    },
    {
      "fecha": "2025-07-16",
      "fecha_imputacion": "2025-07-22",
      "no_fact": "E310007843141",
      "rnc": "101602465",
      "lugar_compra": "BRAVO S.A",
      "moneda": "RD$",
      "itbis": 190.99,
      "factura_total": 1817.0,
      "tasa_conversion": 1.0,
      "monto_convertido_rd": 1817.0
    },
    {
      "fecha": "2025-07-18",
      "fecha_imputacion": "2025-07-22",
      "no_fact": "390240",
      "rnc": "101617233",
      "lugar_compra": "PREMIUM & CO SRL",
      "moneda": "RD$",
      "itbis": 1398.33,
      "factura_total": 8444.0,
      "tasa_conversion": 1.0,
      "monto_convertido_rd": 8444.0
    },
    {
      "fecha": "2025-07-18",
      "fecha_imputacion": "2025-07-22",
      "no_fact": "0002845",
      "rnc": "101068282",
      "lugar_compra": "FERRETERIA SAN MIGUEL",
      "moneda": "RD$",
      "itbis": 290.59,
      "factura_total": 1905.0,
      "tasa_conversion": 1.0,
      "monto_convertido_rd": 1905.0
    },
    {
      "fecha": "2025-07-09",
      "fecha_imputacion": "2025-07-22",
      "no_fact": "B0100073194",
      "rnc": "130343561",
      "lugar_compra": "D COLOR AUTO PAINT",
      "moneda": "RD$",
      "itbis": 2010.52,
      "factura_total": 13180.06,
      "tasa_conversion": 1.0,
      "monto_convertido_rd": 13180.06
    },
    {
      "fecha": "2025-07-23",
      "fecha_imputacion": "2025-07-23",
      "no_fact": "B0100019440",
      "rnc": "131768522",
      "lugar_compra": "SH PREMIUM BEAUTY MARKET SRL",
      "moneda": "RD$",
      "itbis": 260.85,
      "factura_total": 1710.0,
      "tasa_conversion": 1.0,
      "monto_convertido_rd": 1710.0
    },
    {
      "fecha": "2025-07-22",
      "fecha_imputacion": "2025-07-23",
      "no_fact": "B0100030944",
      "rnc": "131412092",
      "lugar_compra": "EL ITALIANO",
      "moneda": "RD$",
      "itbis": 263.52,
      "factura_total": 1873.92,
      "tasa_conversion": 1.0,
      "monto_convertido_rd": 1873.92
    },
    {
      "fecha": "2025-07-20",
      "fecha_imputacion": "2025-07-23",
      "no_fact": "B0100846751",
      "rnc": "131163041",
      "lugar_compra": "POLLOS VICTORINA",
      "moneda": "RD$",
      "itbis": 204.41,
      "factura_total": 1340.0,
      "tasa_conversion": 1.0,
      "monto_convertido_rd": 1340.0
    },
    {
      "fecha": "2025-07-25",
      "fecha_imputacion": "2025-07-31",
      "no_fact": "b0100008514",
      "rnc": "131540155",
      "lugar_compra": "MIDAS SEGUROS",
      "moneda": "RD$",
      "itbis": 684.14,
      "factura_total": 4960.0,
      "tasa_conversion": 1.0,
      "monto_convertido_rd": 4960.0
    },
    {
      "fecha": "2025-07-01",
      "fecha_imputacion": "2025-07-31",
      "no_fact": "4464928",
      "rnc": "102017174",
      "lugar_compra": "HUMANO SEGUROS",
      "moneda": "RD$",
      "itbis": 0.0,
      "factura_total": 8004.65,
      "tasa_conversion": 1.0,
      "monto_convertido_rd": 8004.65
    },
    {
      "fecha": "2025-07-30",
      "fecha_imputacion": "2025-07-31",
      "no_fact": "1532496",
      "rnc": "101588561",
      "lugar_compra": "FERRETERIA CIMA",
      "moneda": "RD$",
      "itbis": 541.98,
      "factura_total": 3553.0,
      "tasa_conversion": 1.0,
      "monto_convertido_rd": 3553.0
    },
    {
      "fecha": "2025-07-21",
      "fecha_imputacion": "2025-07-31",
      "no_fact": "E310007907944",
      "rnc": "101602465",
      "lugar_compra": "BRAVO S.A",
      "moneda": "RD$",
      "itbis": 228.81,
      "factura_total": 3659.0,
      "tasa_conversion": 1.0,
      "monto_convertido_rd": 3659.0
    },
    {
      "fecha": "2025-07-26",
      "fecha_imputacion": "2025-07-31",
      "no_fact": "606818",
      "rnc": "131952526",
      "lugar_compra": "LERRAFE SRL",
      "moneda": "RD$",
      "itbis": 83.89,
      "factura_total": 549.99,
      "tasa_conversion": 1.0,
      "monto_convertido_rd": 549.99
    },
    {
      "fecha": "2025-07-26",
      "fecha_imputacion": "2025-07-31",
      "no_fact": "B0100518641",
      "rnc": "101767766",
      "lugar_compra": "ESTACION AXXON",
      "moneda": "RD$",
      "itbis": 0.0,
      "factura_total": 3900.0,
      "tasa_conversion": 1.0,
      "monto_convertido_rd": 3900.0
    },
    {
      "fecha": "2025-07-16",
      "fecha_imputacion": "2025-07-31",
      "no_fact": "1159976",
      "rnc": "101068744",
      "lugar_compra": "TOTAL ENERGIES",
      "moneda": "RD$",
      "itbis": 0.0,
      "factura_total": 1000.0,
      "tasa_conversion": 1.0,
      "monto_convertido_rd": 1000.0
    },
    {
      "fecha": "2025-07-28",
      "fecha_imputacion": "2025-07-31",
      "no_fact": "151866",
      "rnc": "130689164",
      "lugar_compra": "SIGMA PETROLEUM CORP",
      "moneda": "RD$",
      "itbis": 0.0,
      "factura_total": 3203.9,
      "tasa_conversion": 1.0,
      "monto_convertido_rd": 3203.9
    },
    {
      "fecha": "2025-07-14",
      "fecha_imputacion": "2025-07-31",
      "no_fact": "E310007905175",
      "rnc": "101602465",
      "lugar_compra": "BRAVO S.A",
      "moneda": "RD$",
      "itbis": 242.45,
      "factura_total": 2489.0,
      "tasa_conversion": 1.0,
      "monto_convertido_rd": 2489.0
    },
    {
      "fecha": "2025-07-26",
      "fecha_imputacion": "2025-07-31",
      "no_fact": "E310008049823",
      "rnc": "101602465",
      "lugar_compra": "BRAVO S.A",
      "moneda": "RD$",
      "itbis": 19.68,
      "factura_total": 1305.0,
      "tasa_conversion": 1.0,
      "monto_convertido_rd": 1305.0
    },
    {
      "fecha": "2025-07-27",
      "fecha_imputacion": "2025-07-31",
      "no_fact": "E310000347691",
      "rnc": "101802456",
      "lugar_compra": "COMPAÑIA DOMINICANA DE HIPERMERCADOS CDH",
      "moneda": "RD$",
      "itbis": 129.81,
      "factura_total": 1100.35,
      "tasa_conversion": 1.0,
      "monto_convertido_rd": 1100.35
    },
    {
      "fecha": "2025-06-24",
      "fecha_imputacion": "2025-07-31",
      "no_fact": "B0119818891",
      "rnc": "101019921",
      "lugar_compra": "CENTRO CUESTA NACIONAL",
      "moneda": "RD$",
      "itbis": 163.16,
      "factura_total": 1178.6,
      "tasa_conversion": 1.0,
      "monto_convertido_rd": 1178.6
    },
    {
      "fecha": "2025-07-28",
      "fecha_imputacion": "2025-07-31",
      "no_fact": "164817",
      "rnc": "130554307",
      "lugar_compra": "LA GOMA AUTO SERVICIO",
      "moneda": "RD$",
      "itbis": 228.9,
      "factura_total": 1500.55,
      "tasa_conversion": 1.0,
      "monto_convertido_rd": 1500.55
    },
    {
      "fecha": "2025-07-27",
      "fecha_imputacion": "2025-07-31",
      "no_fact": "743769",
      "rnc": "130064423",
      "lugar_compra": "FARMACIA MEDICAR GBC SRL",
      "moneda": "RD$",
      "itbis": 0.0,
      "factura_total": 4213.04,
      "tasa_conversion": 1.0,
      "monto_convertido_rd": 4213.04
    },
    {
      "fecha": "2025-07-12",
      "fecha_imputacion": "2025-07-31",
      "no_fact": "E310000341529",
      "rnc": "101802456",
      "lugar_compra": "COMPAÑIA DOMINICANA DE HIPERMERCADOS CDH",
      "moneda": "RD$",
      "itbis": 146.42,
      "factura_total": 959.9,
      "tasa_conversion": 1.0,
      "monto_convertido_rd": 959.9
    },
    {
      "fecha": "2025-07-11",
      "fecha_imputacion": "2025-07-31",
      "no_fact": "E310000230752",
      "rnc": "124003091",
      "lugar_compra": "KENTUCKY FOODS GROUP LIMITED",
      "moneda": "RD$",
      "itbis": 165.36,
      "factura_total": 1084.0,
      "tasa_conversion": 1.0,
      "monto_convertido_rd": 1084.0
    },
    {
      "fecha": "2025-07-21",
      "fecha_imputacion": "2025-07-31",
      "no_fact": "741146",
      "rnc": "130064423",
      "lugar_compra": "FARMACIA MEDICAR GBC SRL",
      "moneda": "RD$",
      "itbis": 0.0,
      "factura_total": 738.7,
      "tasa_conversion": 1.0,
      "monto_convertido_rd": 738.7
    },
    {
      "fecha": "2025-07-21",
      "fecha_imputacion": "2025-07-31",
      "no_fact": "741235",
      "rnc": "130064423",
      "lugar_compra": "FARMACIA MEDICAR GBC SRL",
      "moneda": "RD$",
      "itbis": 0.0,
      "factura_total": 962.8,
      "tasa_conversion": 1.0,
      "monto_convertido_rd": 962.8
    },
    {
      "fecha": "2025-07-25",
      "fecha_imputacion": "2025-07-31",
      "no_fact": "B0119829102",
      "rnc": "101019921",
      "lugar_compra": "CENTRO CUESTA NACIONAL",
      "moneda": "RD$",
      "itbis": 355.7,
      "factura_total": 2527.36,
      "tasa_conversion": 1.0,
      "monto_convertido_rd": 2527.36
    },
    {
      "fecha": "2025-07-23",
      "fecha_imputacion": "2025-07-31",
      "no_fact": "1716900",
      "rnc": "101019921",
      "lugar_compra": "CENTRO CUESTA NACIONAL",
      "moneda": "RD$",
      "itbis": 152.64,
      "factura_total": 1225.45,
      "tasa_conversion": 1.0,
      "monto_convertido_rd": 1225.45
    },
    {
      "fecha": "2025-07-26",
      "fecha_imputacion": "2025-07-31",
      "no_fact": "B0100676080",
      "rnc": "401051712",
      "lugar_compra": "CLUB DEPORTIVO NAVO",
      "moneda": "RD$",
      "itbis": 303.0,
      "factura_total": 3333.0,
      "tasa_conversion": 1.0,
      "monto_convertido_rd": 3333.0
    },
    {
      "fecha": "2025-07-16",
      "fecha_imputacion": "2025-07-31",
      "no_fact": "E310000236511",
      "rnc": "124003091",
      "lugar_compra": "KENTUCKY FOODS GROUP LIMITED",
      "moneda": "RD$",
      "itbis": 172.69,
      "factura_total": 1228.01,
      "tasa_conversion": 1.0,
      "monto_convertido_rd": 1228.01
    },
    {
      "fecha": "2025-07-28",
      "fecha_imputacion": "2025-07-31",
      "no_fact": "164802",
      "rnc": "130554307",
      "lugar_compra": "LA GOMA AUTO SERVICIO",
      "moneda": "RD$",
      "itbis": 3166.2,
      "factura_total": 20756.2,
      "tasa_conversion": 1.0,
      "monto_convertido_rd": 20756.2
    },
    {
      "fecha": "2025-07-28",
      "fecha_imputacion": "2025-07-31",
      "no_fact": "422933",
      "rnc": "131599826",
      "lugar_compra": "ASADERO DONA PULA",
      "moneda": "RD$",
      "itbis": 400.63,
      "factura_total": 222.57,
      "tasa_conversion": 1.0,
      "monto_convertido_rd": 222.57
    },
    {
      "fecha": "2025-07-24",
      "fecha_imputacion": "2025-07-31",
      "no_fact": "1531301",
      "rnc": "101588561",
      "lugar_compra": "FERRETERIA CIMA",
      "moneda": "RD$",
      "itbis": 655.17,
      "factura_total": 4295.0,
      "tasa_conversion": 1.0,
      "monto_convertido_rd": 4295.0
    },
    {
      "fecha": "2025-08-14",
      "fecha_imputacion": "2025-08-28",
      "no_fact": "64383",
      "rnc": "101003693",
      "lugar_compra": "CORRIPIO",
      "moneda": "RD$",
      "itbis": 2592.0,
      "factura_total": 16994.0,
      "tasa_conversion": 1.0,
      "monto_convertido_rd": 16994.0
    },
    {
      "fecha": "2025-08-15",
      "fecha_imputacion": "2025-08-28",
      "no_fact": "392573",
      "rnc": "101617233",
      "lugar_compra": "PREMIUM & CO SRL",
      "moneda": "RD$",
      "itbis": 1747.91,
      "factura_total": 11458.51,
      "tasa_conversion": 1.0,
      "monto_convertido_rd": 11458.51
    },
    {
      "fecha": "2025-08-26",
      "fecha_imputacion": "2025-08-28",
      "no_fact": "B0102864025",
      "rnc": "101171111",
      "lugar_compra": "ELECTROLAMA",
      "moneda": "RD$",
      "itbis": 1875.51,
      "factura_total": 12295.0,
      "tasa_conversion": 1.0,
      "monto_convertido_rd": 12295.0
    },
    {
      "fecha": "2025-08-09",
      "fecha_imputacion": "2025-09-01",
      "no_fact": "",
      "rnc": "101801875",
      "lugar_compra": "PRICESMART",
      "moneda": "RD$",
      "itbis": 365.33,
      "factura_total": 3105.85,
      "tasa_conversion": 1.0,
      "monto_convertido_rd": 3105.85
    },
    {
      "fecha": "2025-08-15",
      "fecha_imputacion": "2025-09-01",
      "no_fact": "",
      "rnc": "101019921",
      "lugar_compra": "CENTRO CUESTA NACIONAL",
      "moneda": "RD$",
      "itbis": 126.28,
      "factura_total": 1152.45,
      "tasa_conversion": 1.0,
      "monto_convertido_rd": 1152.45
    },
    {
      "fecha": "2025-08-12",
      "fecha_imputacion": "2025-09-01",
      "no_fact": "",
      "rnc": "101602465",
      "lugar_compra": "BRAVO S.A",
      "moneda": "RD$",
      "itbis": 159.46,
      "factura_total": 2274.0,
      "tasa_conversion": 1.0,
      "monto_convertido_rd": 2274.0
    },
    {
      "fecha": "2025-08-22",
      "fecha_imputacion": "2025-09-01",
      "no_fact": "",
      "rnc": "101068744",
      "lugar_compra": "TOTALENERGIES",
      "moneda": "RD$",
      "itbis": 0.0,
      "factura_total": 3820.3,
      "tasa_conversion": 1.0,
      "monto_convertido_rd": 3820.3
    },
    {
      "fecha": "2025-08-22",
      "fecha_imputacion": "2025-09-01",
      "no_fact": "",
      "rnc": "132881869",
      "lugar_compra": "BELLAMAR SMOKEHOUSE",
      "moneda": "RD$",
      "itbis": 217.37,
      "factura_total": 1425.0,
      "tasa_conversion": 1.0,
      "monto_convertido_rd": 1425.0
    },
    {
      "fecha": "2025-08-22",
      "fecha_imputacion": "2025-09-01",
      "no_fact": "",
      "rnc": "132881869",
      "lugar_compra": "BELLAMAR SMOKEHOUSE",
      "moneda": "RD$",
      "itbis": 134.48,
      "factura_total": 881.6,
      "tasa_conversion": 1.0,
      "monto_convertido_rd": 881.6
    },
    {
      "fecha": "2025-08-15",
      "fecha_imputacion": "2025-09-01",
      "no_fact": "",
      "rnc": "130682348",
      "lugar_compra": "EL TAQUITO NORTEÑO",
      "moneda": "RD$",
      "itbis": 561.6,
      "factura_total": 3993.6,
      "tasa_conversion": 1.0,
      "monto_convertido_rd": 3993.6
    },
    {
      "fecha": "2025-08-15",
      "fecha_imputacion": "2025-09-01",
      "no_fact": "",
      "rnc": "130682348",
      "lugar_compra": "EL TAQUITO NORTEÑO",
      "moneda": "RD$",
      "itbis": 607.5,
      "factura_total": 4408.0,
      "tasa_conversion": 1.0,
      "monto_convertido_rd": 4408.0
    },
    {
      "fecha": "2025-08-11",
      "fecha_imputacion": "2025-09-01",
      "no_fact": "",
      "rnc": "132460342",
      "lugar_compra": "GRAPAN DOMINICANA SRL",
      "moneda": "RD$",
      "itbis": 421.92,
      "factura_total": 3000.32,
      "tasa_conversion": 1.0,
      "monto_convertido_rd": 3000.32
    },
    {
      "fecha": "2025-08-18",
      "fecha_imputacion": "2025-09-01",
      "no_fact": "",
      "rnc": "101602465",
      "lugar_compra": "BRAVO S.A",
      "moneda": "RD$",
      "itbis": 890.83,
      "factura_total": 9310.0,
      "tasa_conversion": 1.0,
      "monto_convertido_rd": 9310.0
    },
    {
      "fecha": "2025-08-18",
      "fecha_imputacion": "2025-09-01",
      "no_fact": "",
      "rnc": "101602465",
      "lugar_compra": "BRAVO S.A",
      "moneda": "RD$",
      "itbis": 76.42,
      "factura_total": 819.0,
      "tasa_conversion": 1.0,
      "monto_convertido_rd": 819.0
    },
    {
      "fecha": "2025-08-18",
      "fecha_imputacion": "2025-09-01",
      "no_fact": "",
      "rnc": "132648366",
      "lugar_compra": "PENDA EXPRESS",
      "moneda": "RD$",
      "itbis": 124.62,
      "factura_total": 816.94,
      "tasa_conversion": 1.0,
      "monto_convertido_rd": 816.94
    },
    {
      "fecha": "2025-08-18",
      "fecha_imputacion": "2025-09-01",
      "no_fact": "",
      "rnc": "131508006",
      "lugar_compra": "JJS FOODTRUCK SRL",
      "moneda": "RD$",
      "itbis": 135.0,
      "factura_total": 1100.02,
      "tasa_conversion": 1.0,
      "monto_convertido_rd": 1100.02
    },
    {
      "fecha": "2025-08-19",
      "fecha_imputacion": "2025-09-01",
      "no_fact": "",
      "rnc": "101132841",
      "lugar_compra": "TRANSAMERICAN HOTELS",
      "moneda": "RD$",
      "itbis": 801.0,
      "factura_total": 5696.0,
      "tasa_conversion": 1.0,
      "monto_convertido_rd": 5696.0
    },
    {
      "fecha": "2025-08-15",
      "fecha_imputacion": "2025-09-01",
      "no_fact": "",
      "rnc": "101802456",
      "lugar_compra": "CARREFOUR",
      "moneda": "RD$",
      "itbis": 122.31,
      "factura_total": 1498.91,
      "tasa_conversion": 1.0,
      "monto_convertido_rd": 1498.91
    },
    {
      "fecha": "2025-08-16",
      "fecha_imputacion": "2025-09-01",
      "no_fact": "",
      "rnc": "401051712",
      "lugar_compra": "CLUB DEPORTIVO NACO",
      "moneda": "RD$",
      "itbis": 342.5,
      "factura_total": 3767.5,
      "tasa_conversion": 1.0,
      "monto_convertido_rd": 3767.5
    },
    {
      "fecha": "2025-08-17",
      "fecha_imputacion": "2025-09-01",
      "no_fact": "",
      "rnc": "401051712",
      "lugar_compra": "CLUB DEPORTIVO NACO",
      "moneda": "RD$",
      "itbis": 305.0,
      "factura_total": 3355.0,
      "tasa_conversion": 1.0,
      "monto_convertido_rd": 3355.0
    },
    {
      "fecha": "2025-08-16",
      "fecha_imputacion": "2025-09-01",
      "no_fact": "",
      "rnc": "131925375",
      "lugar_compra": "HUMUS SABORES DEL DESIERTO",
      "moneda": "RD$",
      "itbis": 102.2,
      "factura_total": 670.0,
      "tasa_conversion": 1.0,
      "monto_convertido_rd": 670.0
    },
    {
      "fecha": "2025-08-16",
      "fecha_imputacion": "2025-09-01",
      "no_fact": "",
      "rnc": "101628431",
      "lugar_compra": "SHELL",
      "moneda": "RD$",
      "itbis": 0.0,
      "factura_total": 1000.0,
      "tasa_conversion": 1.0,
      "monto_convertido_rd": 1000.0
    },
    {
      "fecha": "2025-08-15",
      "fecha_imputacion": "2025-09-01",
      "no_fact": "",
      "rnc": "101068744",
      "lugar_compra": "TOTALENERGIES",
      "moneda": "RD$",
      "itbis": 0.0,
      "factura_total": 2000.0,
      "tasa_conversion": 1.0,
      "monto_convertido_rd": 2000.0
    },
    {
      "fecha": "2025-08-15",
      "fecha_imputacion": "2025-09-01",
      "no_fact": "",
      "rnc": "101068744",
      "lugar_compra": "TOTALENERGIES",
      "moneda": "RD$",
      "itbis": 0.0,
      "factura_total": 1500.0,
      "tasa_conversion": 1.0,
      "monto_convertido_rd": 1500.0
    },
    {
      "fecha": "2025-07-06",
      "fecha_imputacion": "2025-09-01",
      "no_fact": "",
      "rnc": "131038913",
      "lugar_compra": "LUBRIPOINT",
      "moneda": "RD$",
      "itbis": 767.3,
      "factura_total": 5029.98,
      "tasa_conversion": 1.0,
      "monto_convertido_rd": 5029.98
    },
    {
      "fecha": "2025-08-26",
      "fecha_imputacion": "2025-09-01",
      "no_fact": "",
      "rnc": "130246491",
      "lugar_compra": "WENDYS",
      "moneda": "RD$",
      "itbis": 152.54,
      "factura_total": 1000.0,
      "tasa_conversion": 1.0,
      "monto_convertido_rd": 1000.0
    },
    {
      "fecha": "2025-07-29",
      "fecha_imputacion": "2025-09-01",
      "no_fact": "",
      "rnc": "130064423",
      "lugar_compra": "FARMACIA MEDICAR GBC",
      "moneda": "RD$",
      "itbis": 0.0,
      "factura_total": 1322.75,
      "tasa_conversion": 1.0,
      "monto_convertido_rd": 1322.75
    },
    {
      "fecha": "2025-08-01",
      "fecha_imputacion": "2025-09-01",
      "no_fact": "",
      "rnc": "101602465",
      "lugar_compra": "BRAVO S.A",
      "moneda": "RD$",
      "itbis": 340.66,
      "factura_total": 4812.0,
      "tasa_conversion": 1.0,
      "monto_convertido_rd": 4812.0
    },
    {
      "fecha": "2025-07-31",
      "fecha_imputacion": "2025-09-01",
      "no_fact": "",
      "rnc": "101602465",
      "lugar_compra": "BRAVO S.A",
      "moneda": "RD$",
      "itbis": 22.73,
      "factura_total": 997.0,
      "tasa_conversion": 1.0,
      "monto_convertido_rd": 997.0
    },
    {
      "fecha": "2025-08-03",
      "fecha_imputacion": "2025-09-01",
      "no_fact": "",
      "rnc": "131458394",
      "lugar_compra": "CAFETERIA TOSTADO",
      "moneda": "RD$",
      "itbis": 235.9,
      "factura_total": 1380.55,
      "tasa_conversion": 1.0,
      "monto_convertido_rd": 1380.55
    },
    {
      "fecha": "2025-07-28",
      "fecha_imputacion": "2025-09-01",
      "no_fact": "",
      "rnc": "124003091",
      "lugar_compra": "KFC",
      "moneda": "RD$",
      "itbis": 168.47,
      "factura_total": 1198.0,
      "tasa_conversion": 1.0,
      "monto_convertido_rd": 1198.0
    },
    {
      "fecha": "2025-07-30",
      "fecha_imputacion": "2025-09-01",
      "no_fact": "",
      "rnc": "101148861",
      "lugar_compra": "BATISSA SRL",
      "moneda": "RD$",
      "itbis": 514.07,
      "factura_total": 3370.01,
      "tasa_conversion": 1.0,
      "monto_convertido_rd": 3370.01
    },
    {
      "fecha": "2025-08-02",
      "fecha_imputacion": "2025-09-01",
      "no_fact": "",
      "rnc": "00112812326",
      "lugar_compra": "ESPAÑOLERIAS",
      "moneda": "RD$",
      "itbis": 610.17,
      "factura_total": 4000.01,
      "tasa_conversion": 1.0,
      "monto_convertido_rd": 4000.01
    },
    {
      "fecha": "2025-07-31",
      "fecha_imputacion": "2025-09-01",
      "no_fact": "",
      "rnc": "101019921",
      "lugar_compra": "CENTRO CUESTA NACIONAL",
      "moneda": "RD$",
      "itbis": 144.56,
      "factura_total": 947.65,
      "tasa_conversion": 1.0,
      "monto_convertido_rd": 947.65
    },
    {
      "fecha": "2025-08-01",
      "fecha_imputacion": "2025-09-01",
      "no_fact": "",
      "rnc": "130772797",
      "lugar_compra": "INVERSIONES EL GALLEGO SRL",
      "moneda": "RD$",
      "itbis": 1324.8,
      "factura_total": 9420.8,
      "tasa_conversion": 1.0,
      "monto_convertido_rd": 9420.8
    },
    {
      "fecha": "2025-08-03",
      "fecha_imputacion": "2025-09-01",
      "no_fact": "",
      "rnc": "131502237",
      "lugar_compra": "GRUPO SATORI CARIBE",
      "moneda": "RD$",
      "itbis": 318.6,
      "factura_total": 2088.6,
      "tasa_conversion": 1.0,
      "monto_convertido_rd": 2088.6
    },
    {
      "fecha": "2025-07-20",
      "fecha_imputacion": "2025-09-01",
      "no_fact": "",
      "rnc": "101019921",
      "lugar_compra": "CENTRO CUESTA NACIONAL",
      "moneda": "RD$",
      "itbis": 30.32,
      "factura_total": 1427.38,
      "tasa_conversion": 1.0,
      "monto_convertido_rd": 1427.38
    },
    {
      "fecha": "2025-08-05",
      "fecha_imputacion": "2025-09-01",
      "no_fact": "",
      "rnc": "101019921",
      "lugar_compra": "CENTRO CUESTA NACIONAL",
      "moneda": "RD$",
      "itbis": 213.07,
      "factura_total": 2011.34,
      "tasa_conversion": 1.0,
      "monto_convertido_rd": 2011.34
    },
    {
      "fecha": "2025-08-01",
      "fecha_imputacion": "2025-09-01",
      "no_fact": "",
      "rnc": "101602465",
      "lugar_compra": "BRAVO S.A",
      "moneda": "RD$",
      "itbis": 181.56,
      "factura_total": 2335.0,
      "tasa_conversion": 1.0,
      "monto_convertido_rd": 2335.0
    },
    {
      "fecha": "2025-08-12",
      "fecha_imputacion": "2025-09-01",
      "no_fact": "",
      "rnc": "131279961",
      "lugar_compra": "TEXACO",
      "moneda": "RD$",
      "itbis": 0.0,
      "factura_total": 1500.0,
      "tasa_conversion": 1.0,
      "monto_convertido_rd": 1500.0
    },
    {
      "fecha": "2025-08-09",
      "fecha_imputacion": "2025-09-01",
      "no_fact": "",
      "rnc": "101019921",
      "lugar_compra": "CENTRO CUESTA NACIONAL",
      "moneda": "RD$",
      "itbis": 254.62,
      "factura_total": 2155.27,
      "tasa_conversion": 1.0,
      "monto_convertido_rd": 2155.27
    },
    {
      "fecha": "2025-08-10",
      "fecha_imputacion": "2025-09-01",
      "no_fact": "",
      "rnc": "130266603",
      "lugar_compra": "DRINKS2GO",
      "moneda": "RD$",
      "itbis": 594.92,
      "factura_total": 3900.0,
      "tasa_conversion": 1.0,
      "monto_convertido_rd": 3900.0
    },
    {
      "fecha": "2025-08-21",
      "fecha_imputacion": "2025-09-01",
      "no_fact": "",
      "rnc": "101796822",
      "lugar_compra": "SIRENA",
      "moneda": "RD$",
      "itbis": 133.48,
      "factura_total": 1164.0,
      "tasa_conversion": 1.0,
      "monto_convertido_rd": 1164.0
    },
    {
      "fecha": "2025-08-18",
      "fecha_imputacion": "2025-09-01",
      "no_fact": "",
      "rnc": "101068744",
      "lugar_compra": "TOTALENERGIES",
      "moneda": "RD$",
      "itbis": 0.0,
      "factura_total": 3920.1,
      "tasa_conversion": 1.0,
      "monto_convertido_rd": 3920.1
    },
    {
      "fecha": "2025-08-28",
      "fecha_imputacion": "2025-09-01",
      "no_fact": "",
      "rnc": "130266603",
      "lugar_compra": "DRINKS2GO",
      "moneda": "RD$",
      "itbis": 549.92,
      "factura_total": 3670.0,
      "tasa_conversion": 1.0,
      "monto_convertido_rd": 3670.0
    },
    {
      "fecha": "2025-08-15",
      "fecha_imputacion": "2025-09-01",
      "no_fact": "",
      "rnc": "101602465",
      "lugar_compra": "BRAVO S.A",
      "moneda": "RD$",
      "itbis": 239.95,
      "factura_total": 3697.0,
      "tasa_conversion": 1.0,
      "monto_convertido_rd": 3697.0
    },
    {
      "fecha": "2025-08-24",
      "fecha_imputacion": "2025-09-01",
      "no_fact": "",
      "rnc": "132881869",
      "lugar_compra": "BELLAMAR SMOKEHOUSE",
      "moneda": "RD$",
      "itbis": 370.49,
      "factura_total": 2634.6,
      "tasa_conversion": 1.0,
      "monto_convertido_rd": 2634.6
    },
    {
      "fecha": "2025-08-17",
      "fecha_imputacion": "2025-09-01",
      "no_fact": "",
      "rnc": "101570611",
      "lugar_compra": "PALAPIZZA",
      "moneda": "RD$",
      "itbis": 298.83,
      "factura_total": 2125.0,
      "tasa_conversion": 1.0,
      "monto_convertido_rd": 2125.0
    },
    {
      "fecha": "2025-08-14",
      "fecha_imputacion": "2025-09-01",
      "no_fact": "",
      "rnc": "101602465",
      "lugar_compra": "BRAVO S.A",
      "moneda": "RD$",
      "itbis": 71.23,
      "factura_total": 1644.0,
      "tasa_conversion": 1.0,
      "monto_convertido_rd": 1644.0
    },
    {
      "fecha": "2025-08-19",
      "fecha_imputacion": "2025-09-01",
      "no_fact": "",
      "rnc": "101602465",
      "lugar_compra": "BRAVO S.A",
      "moneda": "RD$",
      "itbis": 63.28,
      "factura_total": 818.0,
      "tasa_conversion": 1.0,
      "monto_convertido_rd": 818.0
    },
    {
      "fecha": "2025-08-11",
      "fecha_imputacion": "2025-09-01",
      "no_fact": "",
      "rnc": "101602465",
      "lugar_compra": "BRAVO S.A",
      "moneda": "RD$",
      "itbis": 399.4,
      "factura_total": 4221.0,
      "tasa_conversion": 1.0,
      "monto_convertido_rd": 4221.0
    },
    {
      "fecha": "2025-08-22",
      "fecha_imputacion": "2025-09-01",
      "no_fact": "",
      "rnc": "101602465",
      "lugar_compra": "BRAVO S.A",
      "moneda": "RD$",
      "itbis": 171.71,
      "factura_total": 1962.0,
      "tasa_conversion": 1.0,
      "monto_convertido_rd": 1962.0
    },
    {
      "fecha": "2025-08-20",
      "fecha_imputacion": "2025-09-01",
      "no_fact": "",
      "rnc": "101602465",
      "lugar_compra": "BRAVO S.A",
      "moneda": "RD$",
      "itbis": 252.69,
      "factura_total": 2190.0,
      "tasa_conversion": 1.0,
      "monto_convertido_rd": 2190.0
    },
    {
      "fecha": "2025-08-25",
      "fecha_imputacion": "2025-09-01",
      "no_fact": "",
      "rnc": "131599826",
      "lugar_compra": "ASADERO DOÑA PULA",
      "moneda": "RD$",
      "itbis": 278.72,
      "factura_total": 1982.01,
      "tasa_conversion": 1.0,
      "monto_convertido_rd": 1982.01
    },
    {
      "fecha": "2025-08-07",
      "fecha_imputacion": "2025-09-01",
      "no_fact": "",
      "rnc": "101068744",
      "lugar_compra": "TOTALENERGIES",
      "moneda": "RD$",
      "itbis": 0.0,
      "factura_total": 1200.0,
      "tasa_conversion": 1.0,
      "monto_convertido_rd": 1200.0
    },
    {
      "fecha": "2025-08-11",
      "fecha_imputacion": "2025-09-01",
      "no_fact": "",
      "rnc": "101802456",
      "lugar_compra": "CARREFOUR",
      "moneda": "RD$",
      "itbis": 185.15,
      "factura_total": 1213.8,
      "tasa_conversion": 1.0,
      "monto_convertido_rd": 1213.8
    },
    {
      "fecha": "2025-08-25",
      "fecha_imputacion": "2025-09-01",
      "no_fact": "",
      "rnc": "102616043",
      "lugar_compra": "GASOLINERA EL EMBRUJO SRL",
      "moneda": "RD$",
      "itbis": 0.0,
      "factura_total": 3000.0,
      "tasa_conversion": 1.0,
      "monto_convertido_rd": 3000.0
    },
    {
      "fecha": "2025-08-23",
      "fecha_imputacion": "2025-09-01",
      "no_fact": "",
      "rnc": "131457192",
      "lugar_compra": "INVERSIONES B UNLIMITED",
      "moneda": "RD$",
      "itbis": 820.8,
      "factura_total": 5836.8,
      "tasa_conversion": 1.0,
      "monto_convertido_rd": 5836.8
    },
    {
      "fecha": "2025-08-27",
      "fecha_imputacion": "2025-09-01",
      "no_fact": "",
      "rnc": "130494959",
      "lugar_compra": "BEACHSIDE INVESTMENTS S.A",
      "moneda": "RD$",
      "itbis": 529.2,
      "factura_total": 3763.2,
      "tasa_conversion": 1.0,
      "monto_convertido_rd": 3763.2
    },
    {
      "fecha": "2025-07-19",
      "fecha_imputacion": "2025-09-01",
      "no_fact": "",
      "rnc": "131327427",
      "lugar_compra": "IMPORTADORA BUENO Y MAS IBM SRL",
      "moneda": "RD$",
      "itbis": 36633.05,
      "factura_total": 240150.0,
      "tasa_conversion": 1.0,
      "monto_convertido_rd": 240150.0
    },
    {
      "fecha": "2025-08-29",
      "fecha_imputacion": "2025-09-01",
      "no_fact": "",
      "rnc": "131315917",
      "lugar_compra": "OrangeTheoryFitness",
      "moneda": "RD$",
      "itbis": 0.0,
      "factura_total": 7933.5,
      "tasa_conversion": 1.0,
      "monto_convertido_rd": 7933.5
    },
    {
      "fecha": "2025-08-27",
      "fecha_imputacion": "2025-09-01",
      "no_fact": "",
      "rnc": "101019921",
      "lugar_compra": "CENTRO CUESTA NACIONAL",
      "moneda": "RD$",
      "itbis": 185.08,
      "factura_total": 2351.64,
      "tasa_conversion": 1.0,
      "monto_convertido_rd": 2351.64
    },
    {
      "fecha": "2025-08-31",
      "fecha_imputacion": "2025-09-01",
      "no_fact": "",
      "rnc": "132127341",
      "lugar_compra": "ANDALE SRL",
      "moneda": "RD$",
      "itbis": 627.3,
      "factura_total": 4460.8,
      "tasa_conversion": 1.0,
      "monto_convertido_rd": 4460.8
    },
    {
      "fecha": "2025-08-29",
      "fecha_imputacion": "2025-09-01",
      "no_fact": "",
      "rnc": "101019921",
      "lugar_compra": "CENTRO CUESTA NACIONAL",
      "moneda": "RD$",
      "itbis": 92.24,
      "factura_total": 1407.84,
      "tasa_conversion": 1.0,
      "monto_convertido_rd": 1407.84
    },
    {
      "fecha": "2025-08-30",
      "fecha_imputacion": "2025-09-01",
      "no_fact": "",
      "rnc": "131925375",
      "lugar_compra": "HUMUS SABORES DEL DESIERTO",
      "moneda": "RD$",
      "itbis": 204.41,
      "factura_total": 1340.0,
      "tasa_conversion": 1.0,
      "monto_convertido_rd": 1340.0
    },
    {
      "fecha": "2025-08-29",
      "fecha_imputacion": "2025-09-01",
      "no_fact": "",
      "rnc": "130803323",
      "lugar_compra": "HELADERIA VALENTINO SRL",
      "moneda": "RD$",
      "itbis": 0.0,
      "factura_total": 925.0,
      "tasa_conversion": 1.0,
      "monto_convertido_rd": 925.0
    },
    {
      "fecha": "2025-08-29",
      "fecha_imputacion": "2025-09-03",
      "no_fact": "B01000000136\r",
      "rnc": "132042751",
      "lugar_compra": "Barnhouse Services",
      "moneda": "RD$",
      "itbis": 34200.0,
      "factura_total": 224200.0,
      "tasa_conversion": 1.0,
      "monto_convertido_rd": 224200.0
    }
  ],
  "available_currencies": [
    "RD$",
    "USD"
  ],
  "rnc_directory": {},
  "itbis_adelantado": "85372.15"
}